pbtlib/__init__.py
pbtlib/setup.py
pbtlib/codec/__init__.py
pbtlib/codec/basecodec.py
pbtlib/codec/custombasecodec.py
pbtlib/codec/complex/__init__.py
pbtlib/codec/complex/doubleintcodec.py
pbtlib/codec/complex/jsoncodec.py
pbtlib/codec/complex/stringcodec.py
pbtlib/codec/complex/vector3dcodec.py
pbtlib/codec/complex/vectorshortcodec.py
pbtlib/codec/complex/vectorstringcodec.py
pbtlib/codec/complex/vectorvector3dcodec.py
pbtlib/codec/custom/__init__.py
pbtlib/codec/custom/battleimfouserpreviewcodec.py
pbtlib/codec/custom/battleinfocodec.py
pbtlib/codec/custom/battlelimitscodec.py
pbtlib/codec/custom/battlenotifiercodec.py
pbtlib/codec/custom/battleusercodec.py
pbtlib/codec/custom/battleuserrewardscodec.py
pbtlib/codec/custom/battleuserstatscodec.py
pbtlib/codec/custom/chatmessagecodec.py
pbtlib/codec/custom/flaginfocodec.py
pbtlib/codec/custom/missioncodec.py
pbtlib/codec/custom/missionrewardcodec.py
pbtlib/codec/custom/missionstreakcodec.py
pbtlib/codec/custom/movecodec.py
pbtlib/codec/custom/rankrangecodec.py
pbtlib/codec/custom/referraldatacodec.py
pbtlib/codec/custom/tankdamagecodec.py
pbtlib/codec/custom/targethitcodec.py
pbtlib/codec/custom/targetpositioncodec.py
pbtlib/codec/custom/turretrotatecodec.py
pbtlib/codec/custom/userstatscodec.py
pbtlib/codec/custom/userstatuscodec.py
pbtlib/codec/factory/__init__.py
pbtlib/codec/factory/multitypecodec.py
pbtlib/codec/factory/vectorcodec.py
pbtlib/codec/primitive/__init__.py
pbtlib/codec/primitive/boolcodec.py
pbtlib/codec/primitive/bytecodec.py
pbtlib/codec/primitive/floatcodec.py
pbtlib/codec/primitive/intcodec.py
pbtlib/codec/primitive/longcodec.py
pbtlib/codec/primitive/shortcodec.py
pbtlib/modules/__init__.py
pbtlib/modules/client/__init__.py
pbtlib/modules/client/asynctankiinstance.py
pbtlib/modules/client/tankiinstance.py
pbtlib/modules/communications/__init__.py
pbtlib/modules/communications/abstractmessage.py
pbtlib/modules/communications/command.py
probotanki_lib-2.1.7.dist-info/METADATA
probotanki_lib-2.1.7.dist-info/WHEEL
probotanki_lib-2.1.7.dist-info/top_level.txt
probotanki_lib-2.1.7.dist-info/RECORD
