Metadata-Version: 2.4
Name: probotanki-lib
Version: 2.1.7
Summary: Core library for ProboTanki providing networking modules and packet handling utilities.
Author-email: Teinc3 <teinc3@gmail.com>
License: Proprietary
Project-URL: Homepage, https://github.com/Teinc3/ProboTanki-Lib
Project-URL: Documentation, https://deepwiki.com/Teinc3/ProboTanki-Lib
Project-URL: Issue Tracker, https://github.com/Teinc3/ProboTanki-Lib/issues
Classifier: Programming Language :: Python :: 3
Classifier: Operating System :: OS Independent
Classifier: Development Status :: 5 - Production/Stable
Requires-Python: >=3.10
Requires-Dist: pysocks
Requires-Dist: aiosocks
Dynamic: requires-dist
